meural_photo_prep/__init__.py
meural_photo_prep/_utils.py
meural_photo_prep-1.0.1.dist-info/LICENSE
meural_photo_prep-1.0.1.dist-info/METADATA
meural_photo_prep-1.0.1.dist-info/WHEEL
meural_photo_prep-1.0.1.dist-info/RECORD
