Metadata-Version: 2.1
Name: meural-photo-prep
Version: 1.0.1
Summary: Module to assist in preparing photos for Netgear's Meural Canvas
Home-page: https://github.com/ironScripter/meural-photo-prep/
Author: James Arnett
Author-email: james.arnett@gmail.com
Requires-Python: >=3.9,<4.0
Classifier: Programming Language :: Python :: 3
Classifier: Programming Language :: Python :: 3.9
Classifier: Programming Language :: Python :: 3.10
Classifier: Programming Language :: Python :: 3.11
Requires-Dist: pillow (>=9.5.0,<10.0.0)
Project-URL: Repository, https://github.com/ironScripter/meural-photo-prep/
